llm_tools_openapi.py
llm_tools_openapi-0.1.1.dist-info/licenses/LICENSE
llm_tools_openapi-0.1.1.dist-info/METADATA
llm_tools_openapi-0.1.1.dist-info/WHEEL
llm_tools_openapi-0.1.1.dist-info/entry_points.txt
llm_tools_openapi-0.1.1.dist-info/top_level.txt
llm_tools_openapi-0.1.1.dist-info/RECORD
