Metadata-Version: 2.4
Name: llm-tools-openapi
Version: 0.1.1
Summary: a plugins that allow to use OpenAPI as a tools
Author: Olivier GG
License-Expression: Apache-2.0
Project-URL: Homepage, https://github.com/oliviergg/llm-tools-openapi
Project-URL: Changelog, https://github.com/oliviergg/llm-tools-openapi/releases
Project-URL: Issues, https://github.com/oliviergg/llm-tools-openapi/issues
Project-URL: CI, https://github.com/oliviergg/llm-tools-openapi/actions
Requires-Python: >=3.9
License-File: LICENSE
Requires-Dist: llm>=0.26
Requires-Dist: requests
Provides-Extra: test
Requires-Dist: pytest; extra == "test"
Requires-Dist: llm-echo>=0.3a1; extra == "test"
Dynamic: license-file
